bz3/__init__.py
bz3/bz3.py
bz3/compression.py
bz3/py.typed
bz3/backends/__init__.py
bz3/backends/cffi/__init__.py
bz3/backends/cffi/_bz3.pyd
bz3/backends/cffi/build.py
bz3/backends/cython/__init__.py
bz3/backends/cython/_bz3.c
bz3/backends/cython/_bz3.pyd
bz3/backends/cython/_bz3.pyi
bz3/backends/cython/_bz3.pyx
bz3/backends/cython/bzip3.pxd
bzip3-0.1.9.dist-info/METADATA
bzip3-0.1.9.dist-info/WHEEL
bzip3-0.1.9.dist-info/top_level.txt
bzip3-0.1.9.dist-info/RECORD
